imdbinfo/__init__.py
imdbinfo/locale.py
imdbinfo/models.py
imdbinfo/parsers.py
imdbinfo/services.py
imdbinfo/transformers.py
imdbinfo-0.7.0.dist-info/licenses/LICENSE
imdbinfo-0.7.0.dist-info/METADATA
imdbinfo-0.7.0.dist-info/WHEEL
imdbinfo-0.7.0.dist-info/top_level.txt
imdbinfo-0.7.0.dist-info/RECORD
