Metadata-Version: 2.4
Name: imdbinfo
Version: 0.7.0
Summary: A Python service for querying IMDb data
Author-email: "@tveronesi" <tveronesi+imdbinfo@gmail.com>
License: MIT License
Project-URL: Homepage, https://tveronesi.github.io/imdbinfo/
Keywords: imdb,movie,information,data
Classifier: Development Status :: 5 - Production/Stable
Classifier: Intended Audience :: Developers
Classifier: License :: OSI Approved :: MIT License
Classifier: Programming Language :: Python :: 3.10
Classifier: Programming Language :: Python :: 3.11
Classifier: Programming Language :: Python :: 3.12
Classifier: Programming Language :: Python :: 3.13
License-File: LICENSE
Requires-Dist: niquests
Requires-Dist: lxml
Requires-Dist: pydantic
Requires-Dist: jmespath
Requires-Dist: deprecated
Provides-Extra: dev
Requires-Dist: pytest>=7.0; extra == "dev"
Requires-Dist: mypy; extra == "dev"
Requires-Dist: ruff; extra == "dev"
Requires-Dist: black; extra == "dev"
Provides-Extra: build
Requires-Dist: build; extra == "build"
Requires-Dist: twine; extra == "build"
Provides-Extra: test
Requires-Dist: pytest>=7.0; extra == "test"
Dynamic: license-file
